AUTHORS
DESCRIPTION
MANIFEST.in
README.md
setup.cfg
setup.py
asyncapp/__init__.py
asyncapp/core.py
asyncapp/serialport.py
asyncapp/server.py
asyncapp/test.py
asyncapp.egg-info/PKG-INFO
asyncapp.egg-info/SOURCES.txt
asyncapp.egg-info/dependency_links.txt
asyncapp.egg-info/top_level.txt