Metadata-Version: 1.1
Name: asyncapp
Version: 0.2.0
Summary: Simple object-oriented asynchronous application wrapper.
Home-page: https://github.com/marcinbor85/asyncapp
Author: Marcin Borowicz
Author-email: marcinbor85@gmail.com
License: MIT
Keywords: asyncapp asynchronous wrapper async app framework template skeleton
Platform: UNKNOWN
Classifier: Development Status :: 5 - Production/Stable
Classifier: License :: OSI Approved :: MIT License
Classifier: Framework :: AsyncIO
Classifier: Natural Language :: English
Classifier: Operating System :: OS Independent
Classifier: Programming Language :: Python :: 3.6
Classifier: Topic :: Software Development :: Libraries :: Python Modules
